clk/.gitignore
clk/__init__.py
clk/__main__.py
clk/_version.py
clk/alias.py
clk/atexit.py
clk/click_helpers.py
clk/colors.py
clk/commandresolver.py
clk/completion.py
clk/config.py
clk/core.py
clk/customcommands.py
clk/decorators.py
clk/externalcommands.py
clk/flow.py
clk/intermediategroup.py
clk/keyrings.py
clk/keyvaluestore.py
clk/launcher.py
clk/lib.org
clk/lib.py
clk/liblp.py
clk/log.py
clk/main.py
clk/monkeypatch.py
clk/netrc.py
clk/overloads.py
clk/plugin.py
clk/profile.py
clk/setup.py
clk/triggers.py
clk/types.py
clk/commands/__init__.py
clk/commands/alias.py
clk/commands/completion.py
clk/commands/describe.py
clk/commands/echo.py
clk/commands/env.py
clk/commands/exec.py
clk/commands/extension.py
clk/commands/flowdep.py
clk/commands/fork.py
clk/commands/help.py
clk/commands/launcher.py
clk/commands/log.py
clk/commands/parameter.py
clk/commands/pip.py
clk/commands/plugin.py
clk/commands/python.py
clk/commands/secret.py
clk/commands/trigger.py
clk/commands/update.py
clk/commands/value.py
clk/commands/command/__init__.py
clk/commands/command/_clk.sh
clk-0.41.1.dist-info/licenses/LICENSE
clk-0.41.1.dist-info/METADATA
clk-0.41.1.dist-info/WHEEL
clk-0.41.1.dist-info/entry_points.txt
clk-0.41.1.dist-info/top_level.txt
clk-0.41.1.dist-info/RECORD
