Metadata-Version: 2.4
Name: clk
Version: 0.41.1
Summary: A framework to help you have an awesome CLI
Author-email: Samuel Loury <konubinixweb@gmail.com>
License-Expression: MIT
Keywords: cli,framework
Requires-Python: >=3.9
License-File: LICENSE
Requires-Dist: click<8.2,>=8
Requires-Dist: click-log
Requires-Dist: click-didyoumean
Requires-Dist: glob2
Requires-Dist: colorama
Requires-Dist: python-dateutil
Requires-Dist: tabulate==0.8.10
Requires-Dist: networkx
Requires-Dist: parsedatetime
Requires-Dist: pydotplus
Requires-Dist: pluginbase
Requires-Dist: appdirs
Requires-Dist: ipdb
Requires-Dist: humanize==4
Requires-Dist: Pygments
Requires-Dist: cached-property
Requires-Dist: requests
Requires-Dist: tqdm
Dynamic: license-file
